[
  {
    "changeuuid": "b02a60ad-1160-40ec-9867-e2ef38939774",
    "stationuuid": "19c92ecb-4a0e-4e5e-bd6e-8a9c40b83d93",
    "serveruuid": "2e7ac974-6b77-45fb-aa41-98ffc642f7eb",
    "name": "Radio Alta",
    "url": "https://transmiss.ion.ovh/listen/alta/radio.mp3",
    "url_resolved": "https://transmiss.ion.ovh/listen/alta/radio.mp3",
    "homepage": "https://transmiss.ion.ovh/public/alta",
    "favicon": "",
    "tags": "gospel",
    "country": "Switzerland",
    "countrycode": "ch",
    "iso_3166_2": "AT-1",
    "state": "Burgenland",
    "language": "french",
    "languagecodes": "fr",
    "votes": 7,
    "lastchangetime": "2025-05-12 22:01:24",
    "lastchangetime_iso8601": "2025-05-12T22:01:24Z",
    "codec": "MP3",
    "bitrate": 128,
    "hls": 0,
    "lastcheckok": 1,
    "lastchecktime": "2025-05-12 22:06:32",
    "lastchecktime_iso8601": "2025-05-12T22:06:32Z",
    "lastcheckoktime": "2025-05-12 22:06:32",
    "lastcheckoktime_iso8601": "2025-05-12T22:06:32Z",
    "lastlocalchecktime": "2025-05-11 23:28:28",
    "lastlocalchecktime_iso8601": "2025-05-11T23:28:28Z",
    "clicktimestamp": "2025-05-10 13:32:16",
    "clicktimestamp_iso8601": "2025-05-10T13:32:16Z",
    "clickcount": 1,
    "clicktrend": 0,
    "ssl_error": 0,
    "geo_lat": 46.31,
    "geo_long": -6.3,
    "has_extended_info": true
  }
]